heartai/__init__.py
heartai/cli.py
heartai/core/__init__.py
heartai/core/analyzer.py
heartai/core/models.py
heartai/core/preprocessing.py
heartai/utils/__init__.py
heartai/utils/helpers.py
heartai/utils/validators.py
heartai/visualization/__init__.py
heartai/visualization/plotter.py
heartai-0.1.0.dist-info/licenses/LICENSE
heartai-0.1.0.dist-info/METADATA
heartai-0.1.0.dist-info/WHEEL
heartai-0.1.0.dist-info/entry_points.txt
heartai-0.1.0.dist-info/top_level.txt
heartai-0.1.0.dist-info/RECORD
