Metadata-Version: 2.4
Name: heartai
Version: 0.1.0
Summary: AI-powered ECG/EKG signal processing and arrhythmia detection library
Home-page: https://github.com/ahmetxhero/AhmetX-HeartAi.git
Author: AhmetXHero
Author-email: AhmetXHero <ahmetxhero@gmail.com>
License: MIT License
Project-URL: Homepage, https://github.com/ahmetxhero/AhmetX-HeartAi
Project-URL: Bug Reports, https://github.com/ahmetxhero/AhmetX-HeartAi/issues
Project-URL: Source, https://github.com/ahmetxhero/AhmetX-HeartAi
Keywords: ecg,ekg,arrhythmia,detection,machine-learning,healthcare,biosignal
Classifier: Development Status :: 3 - Alpha
Classifier: Intended Audience :: Healthcare Industry
Classifier: Intended Audience :: Science/Research
Classifier: License :: OSI Approved :: MIT License
Classifier: Operating System :: OS Independent
Classifier: Programming Language :: Python :: 3
Classifier: Programming Language :: Python :: 3.8
Classifier: Programming Language :: Python :: 3.9
Classifier: Programming Language :: Python :: 3.10
Classifier: Programming Language :: Python :: 3.11
Classifier: Programming Language :: Python :: 3.12
Classifier: Topic :: Scientific/Engineering :: Medical Science Apps.
Classifier: Topic :: Scientific/Engineering :: Artificial Intelligence
Requires-Python: >=3.8
License-File: LICENSE
Requires-Dist: numpy>=1.21.0
Requires-Dist: scipy>=1.7.0
Requires-Dist: pandas>=1.3.0
Requires-Dist: scikit-learn>=1.0.0
Requires-Dist: joblib>=1.1.0
Requires-Dist: matplotlib>=3.5.0
Requires-Dist: seaborn>=0.11.0
Requires-Dist: click>=8.0.0
Requires-Dist: rich>=12.0.0
Requires-Dist: pydantic>=1.8.0
Dynamic: author
Dynamic: home-page
Dynamic: license-file
Dynamic: requires-python
